LICENSE
README.md
setup.py
miasm/VERSION
miasm/__init__.py
miasm.egg-info/PKG-INFO
miasm.egg-info/SOURCES.txt
miasm.egg-info/dependency_links.txt
miasm.egg-info/requires.txt
miasm.egg-info/top_level.txt
miasm/analysis/__init__.py
miasm/analysis/apiset.py
miasm/analysis/binary.py
miasm/analysis/cst_propag.py
miasm/analysis/data_analysis.py
miasm/analysis/data_flow.py
miasm/analysis/debugging.py
miasm/analysis/depgraph.py
miasm/analysis/disasm_cb.py
miasm/analysis/dse.py
miasm/analysis/expression_range.py
miasm/analysis/gdbserver.py
miasm/analysis/machine.py
miasm/analysis/modularintervals.py
miasm/analysis/outofssa.py
miasm/analysis/sandbox.py
miasm/analysis/simplifier.py
miasm/analysis/ssa.py
miasm/arch/__init__.py
miasm/arch/aarch64/__init__.py
miasm/arch/aarch64/arch.py
miasm/arch/aarch64/disasm.py
miasm/arch/aarch64/jit.py
miasm/arch/aarch64/lifter_model_call.py
miasm/arch/aarch64/regs.py
miasm/arch/aarch64/sem.py
miasm/arch/arm/__init__.py
miasm/arch/arm/arch.py
miasm/arch/arm/disasm.py
miasm/arch/arm/jit.py
miasm/arch/arm/lifter_model_call.py
miasm/arch/arm/regs.py
miasm/arch/arm/sem.py
miasm/arch/mep/__init__.py
miasm/arch/mep/arch.py
miasm/arch/mep/disasm.py
miasm/arch/mep/jit.py
miasm/arch/mep/lifter_model_call.py
miasm/arch/mep/regs.py
miasm/arch/mep/sem.py
miasm/arch/mips32/__init__.py
miasm/arch/mips32/arch.py
miasm/arch/mips32/disasm.py
miasm/arch/mips32/jit.py
miasm/arch/mips32/lifter_model_call.py
miasm/arch/mips32/regs.py
miasm/arch/mips32/sem.py
miasm/arch/msp430/__init__.py
miasm/arch/msp430/arch.py
miasm/arch/msp430/ctype.py
miasm/arch/msp430/disasm.py
miasm/arch/msp430/jit.py
miasm/arch/msp430/lifter_model_call.py
miasm/arch/msp430/regs.py
miasm/arch/msp430/sem.py
miasm/arch/ppc/__init__.py
miasm/arch/ppc/arch.py
miasm/arch/ppc/disasm.py
miasm/arch/ppc/jit.py
miasm/arch/ppc/lifter_model_call.py
miasm/arch/ppc/regs.py
miasm/arch/ppc/sem.py
miasm/arch/sh4/__init__.py
miasm/arch/sh4/arch.py
miasm/arch/sh4/regs.py
miasm/arch/x86/__init__.py
miasm/arch/x86/arch.py
miasm/arch/x86/ctype.py
miasm/arch/x86/disasm.py
miasm/arch/x86/jit.py
miasm/arch/x86/lifter_model_call.py
miasm/arch/x86/regs.py
