Metadata-Version: 2.1
Name: miasm
Version: 0.1.5
Summary: Machine code manipulation library
Home-page: http://miasm.re
Author: Fabrice Desclaux
Author-email: serpilliere@droid-corp.org
License: GPLv2
Keywords: reverse engineering,disassembler,emulator,symbolic execution,intermediate representation,assembler
Classifier: Programming Language :: Python :: 2
Classifier: Programming Language :: Python :: 3
Classifier: Programming Language :: Python :: 2.7
Classifier: Programming Language :: Python :: 3.6
License-File: LICENSE
